Quiz4_fibo/__init__.py
Quiz4_fibo/quiz fr fr.py
Quiz4_Fibo_mamiko-0.0.1.dist-info/LICENSE.txt
Quiz4_Fibo_mamiko-0.0.1.dist-info/METADATA
Quiz4_Fibo_mamiko-0.0.1.dist-info/WHEEL
Quiz4_Fibo_mamiko-0.0.1.dist-info/top_level.txt
Quiz4_Fibo_mamiko-0.0.1.dist-info/RECORD
