Metadata-Version: 2.1
Name: Quiz4-Fibo-mamiko
Version: 0.0.1
Summary: no purpose head empty
Author: savesum
Author-email: luka.donadze.1@btu.edu.ge
Classifier: Programming Language :: Python :: 3
Classifier: License :: OSI Approved :: MIT License
Classifier: Operating System :: OS Independent
Requires-Python: >=3.6
License-File: LICENSE.txt
